batmutant/__init.py__
batmutant/generate_mutant_features.py
batmutant/peptide2index.py
batmutant/pooled_inference.py
batmutant/pooled_inference_weights_only.py
batmutant/train.py
batmutant/data/AA_matrices/blosum100.csv
batmutant/data/AA_matrices/blosum30.csv
batmutant/data/AA_matrices/blosum35.csv
batmutant/data/AA_matrices/blosum40.csv
batmutant/data/AA_matrices/blosum45.csv
batmutant/data/AA_matrices/blosum50.csv
batmutant/data/AA_matrices/blosum55.csv
batmutant/data/AA_matrices/blosum60.csv
batmutant/data/AA_matrices/blosum62.csv
batmutant/data/AA_matrices/blosum65.csv
batmutant/data/AA_matrices/blosum70.csv
batmutant/data/AA_matrices/blosum75.csv
batmutant/data/AA_matrices/blosum80.csv
batmutant/data/AA_matrices/blosum85.csv
batmutant/data/AA_matrices/blosum90.csv
batmutant/data/AA_matrices/dayhoff.csv
batmutant/data/AA_matrices/gonnet.csv
batmutant/data/AA_matrices/hamming.csv
batmutant/data/AA_matrices/pam10.csv
batmutant/data/AA_matrices/pam100.csv
batmutant/data/AA_matrices/pam110.csv
batmutant/data/AA_matrices/pam120.csv
batmutant/data/AA_matrices/pam130.csv
batmutant/data/AA_matrices/pam140.csv
batmutant/data/AA_matrices/pam150.csv
batmutant/data/AA_matrices/pam160.csv
batmutant/data/AA_matrices/pam170.csv
batmutant/data/AA_matrices/pam180.csv
batmutant/data/AA_matrices/pam190.csv
batmutant/data/AA_matrices/pam20.csv
batmutant/data/AA_matrices/pam200.csv
batmutant/data/AA_matrices/pam210.csv
batmutant/data/AA_matrices/pam220.csv
batmutant/data/AA_matrices/pam230.csv
batmutant/data/AA_matrices/pam240.csv
batmutant/data/AA_matrices/pam250.csv
batmutant/data/AA_matrices/pam260.csv
batmutant/data/AA_matrices/pam270.csv
batmutant/data/AA_matrices/pam280.csv
batmutant/data/AA_matrices/pam290.csv
batmutant/data/AA_matrices/pam30.csv
batmutant/data/AA_matrices/pam300.csv
batmutant/data/AA_matrices/pam310.csv
batmutant/data/AA_matrices/pam320.csv
batmutant/data/AA_matrices/pam330.csv
batmutant/data/AA_matrices/pam340.csv
batmutant/data/AA_matrices/pam350.csv
batmutant-0.0.4.dist-info/METADATA
batmutant-0.0.4.dist-info/WHEEL
batmutant-0.0.4.dist-info/licenses/LICENSE.txt
batmutant-0.0.4.dist-info/RECORD
